weatherlink/__init__.py
weatherlink/handler.py
WeatherLink-1.1.10.dist-info/METADATA
WeatherLink-1.1.10.dist-info/WHEEL
WeatherLink-1.1.10.dist-info/top_level.txt
WeatherLink-1.1.10.dist-info/RECORD
